muban_cli/__init__.py
muban_cli/__main__.py
muban_cli/api.py
muban_cli/auth.py
muban_cli/cli.py
muban_cli/config.py
muban_cli/exceptions.py
muban_cli/packager.py
muban_cli/py.typed
muban_cli/utils.py
muban_cli/commands/__init__.py
muban_cli/commands/admin.py
muban_cli/commands/async_ops.py
muban_cli/commands/audit.py
muban_cli/commands/auth.py
muban_cli/commands/generate.py
muban_cli/commands/package.py
muban_cli/commands/resources.py
muban_cli/commands/settings.py
muban_cli/commands/templates.py
muban_cli/commands/users.py
muban_cli-1.2.1.dist-info/licenses/LICENSE
muban_cli-1.2.1.dist-info/METADATA
muban_cli-1.2.1.dist-info/WHEEL
muban_cli-1.2.1.dist-info/entry_points.txt
muban_cli-1.2.1.dist-info/top_level.txt
muban_cli-1.2.1.dist-info/RECORD
